cpolar_connect/__init__.py
cpolar_connect/auth.py
cpolar_connect/cli.py
cpolar_connect/config.py
cpolar_connect/doctor.py
cpolar_connect/exceptions.py
cpolar_connect/i18n.py
cpolar_connect/ssh.py
cpolar_connect/tunnel.py
cpolar_connect-0.1.2.dist-info/METADATA
cpolar_connect-0.1.2.dist-info/WHEEL
cpolar_connect-0.1.2.dist-info/entry_points.txt
cpolar_connect-0.1.2.dist-info/licenses/LICENSE
cpolar_connect-0.1.2.dist-info/RECORD
