Metadata-Version: 2.4
Name: cpolar-connect
Version: 0.1.2
Summary: Easy-to-use CLI tool for cpolar tunnel management and SSH connections
Project-URL: Homepage, https://github.com/Hoper-J/cpolar-connect
Project-URL: Repository, https://github.com/Hoper-J/cpolar-connect.git
Project-URL: Issues, https://github.com/Hoper-J/cpolar-connect/issues
Author-email: Hoper_J <hoper.hw@gmail.com>
License: MIT License
License-File: LICENSE
Keywords: automation,cli,cpolar,ssh,tunnel
Classifier: Development Status :: 4 - Beta
Classifier: Environment :: Console
Classifier: Intended Audience :: Developers
Classifier: License :: OSI Approved :: MIT License
Classifier: Operating System :: OS Independent
Classifier: Topic :: System :: Networking
Classifier: Topic :: Utilities
Requires-Python: >=3.8
Requires-Dist: beautifulsoup4>=4.11.0
Requires-Dist: click>=8.0.0
Requires-Dist: keyring>=24.0.0
Requires-Dist: paramiko>=2.11.0
Requires-Dist: pydantic>=2.0.0
Requires-Dist: requests>=2.28.0
Requires-Dist: rich>=13.0.0
Provides-Extra: dev
Requires-Dist: black>=23.0.0; extra == 'dev'
Requires-Dist: isort>=5.12.0; extra == 'dev'
Requires-Dist: mypy>=1.0.0; extra == 'dev'
Requires-Dist: pre-commit>=3.0.0; extra == 'dev'
Requires-Dist: pytest-cov>=4.0.0; extra == 'dev'
Requires-Dist: pytest>=7.0.0; extra == 'dev'
